[{"badge_img":"./img/after-hours.jpg","title":"After Hours","subtitle":"Just five more minutes, mom!","description":"Awarded to those dedicated developers who don't understand the meaning of home time.","recipient":[{"avatar":"https://bitbucket.org/account/adrianl/avatar/32/","username":"Adrian Lansdown","date":"Tuesday, January 24, 2017 8:15 PM"}]},{"badge_img":"./img/after-hours.jpg","title":"After Hours","subtitle":"Just five more minutes, mom!","description":"Awarded to those dedicated developers who don't understand the meaning of home time.","recipient":[{"avatar":"https://bitbucket.org/account/adrianl/avatar/32/","username":"Adrian Lansdown","date":"Tuesday, January 24, 2017 8:14 PM"}]},{"badge_img":"./img/after-hours.jpg","title":"After Hours","subtitle":"Just five more minutes, mom!","description":"Awarded to those dedicated developers who don't understand the meaning of home time.","recipient":[{"avatar":"https://bitbucket.org/account/adrianl/avatar/32/","username":"Adrian Lansdown","date":"Tuesday, January 24, 2017 7:18 PM"}]},{"badge_img":"./img/after-hours.jpg","title":"After Hours","subtitle":"Just five more minutes, mom!","description":"Awarded to those dedicated developers who don't understand the meaning of home time.","recipient":[{"avatar":"https://bitbucket.org/account/vishalvazkar/avatar/32/","username":"vishal vazkar","date":"Thursday, January 26, 2017 7:05 PM"}]},{"badge_img":"./img/after-hours.jpg","title":"After Hours","subtitle":"Just five more minutes, mom!","description":"Awarded to those dedicated developers who don't understand the meaning of home time.","recipient":[{"avatar":"https://bitbucket.org/account/vishalvazkar/avatar/32/","username":"vishal vazkar","date":"Thursday, January 26, 2017 6:35 PM"}]},{"badge_img":"./img/after-hours.jpg","title":"After Hours","subtitle":"Just five more minutes, mom!","description":"Awarded to those dedicated developers who don't understand the meaning of home time.","recipient":[{"avatar":"https://bitbucket.org/account/vishalvazkar/avatar/32/","username":"vishal vazkar","date":"Thursday, January 26, 2017 6:30 PM"}]},{"badge_img":"./img/after-hours.jpg","title":"After Hours","subtitle":"Just five more minutes, mom!","description":"Awarded to those dedicated developers who don't understand the meaning of home time.","recipient":[{"avatar":"https://bitbucket.org/account/vishalvazkar/avatar/32/","username":"vishal vazkar","date":"Thursday, January 26, 2017 6:26 PM"}]},{"badge_img":"./img/after-hours.jpg","title":"After Hours","subtitle":"Just five more minutes, mom!","description":"Awarded to those dedicated developers who don't understand the meaning of home time.","recipient":[{"avatar":"https://bitbucket.org/account/vishalvazkar/avatar/32/","username":"vishal vazkar","date":"Thursday, January 26, 2017 6:18 PM"}]},{"badge_img":"./img/after-hours.jpg","title":"After Hours","subtitle":"Just five more minutes, mom!","description":"Awarded to those dedicated developers who don't understand the meaning of home time.","recipient":[{"avatar":"https://bitbucket.org/account/vishalvazkar/avatar/32/","username":"vishal vazkar","date":"Thursday, January 26, 2017 6:18 PM"}]},{"badge_img":"./img/after-hours.jpg","title":"After Hours","subtitle":"Just five more minutes, mom!","description":"Awarded to those dedicated developers who don't understand the meaning of home time.","recipient":[{"avatar":"https://bitbucket.org/account/vishalvazkar/avatar/32/","username":"vishal vazkar","date":"Thursday, January 26, 2017 6:17 PM"}]},{"badge_img":"./img/after-hours.jpg","title":"After Hours","subtitle":"Just five more minutes, mom!","description":"Awarded to those dedicated developers who don't understand the meaning of home time.","recipient":[{"avatar":"https://bitbucket.org/account/vishalvazkar/avatar/32/","username":"vishal vazkar","date":"Thursday, January 26, 2017 6:15 PM"}]},{"badge_img":"./img/after-hours.jpg","title":"After Hours","subtitle":"Just five more minutes, mom!","description":"Awarded to those dedicated developers who don't understand the meaning of home time.","recipient":[{"avatar":"https://bitbucket.org/account/vishalvazkar/avatar/32/","username":"vishal vazkar","date":"Thursday, January 26, 2017 6:12 PM"}]},{"badge_img":"./img/after-hours.jpg","title":"After Hours","subtitle":"Just five more minutes, mom!","description":"Awarded to those dedicated developers who don't understand the meaning of home time.","recipient":[{"avatar":"https://bitbucket.org/account/vishalvazkar/avatar/32/","username":"vishal vazkar","date":"Thursday, January 26, 2017 6:11 PM"}]},{"badge_img":"./img/after-hours.jpg","title":"After Hours","subtitle":"Just five more minutes, mom!","description":"Awarded to those dedicated developers who don't understand the meaning of home time.","recipient":[{"avatar":"https://bitbucket.org/account/vishalvazkar/avatar/32/","username":"vishal vazkar","date":"Thursday, January 26, 2017 6:10 PM"}]},{"badge_img":"./img/after-hours.jpg","title":"After Hours","subtitle":"Just five more minutes, mom!","description":"Awarded to those dedicated developers who don't understand the meaning of home time.","recipient":[{"avatar":"https://bitbucket.org/account/vishalvazkar/avatar/32/","username":"vishal vazkar","date":"Monday, January 23, 2017 6:25 PM"}]},{"badge_img":"./img/weekend.jpg","title":"Weekend Coder","subtitle":"Why stop just because it's the weekend?","description":"Awarded to those dedicated developers who don't understand the meaning of downtime.","recipient":[{"avatar":"https://bitbucket.org/account/vishalvazkar/avatar/32/","username":"vishal vazkar","date":"Saturday, January 28, 2017 10:28 PM"}]},{"badge_img":"./img/weekend.jpg","title":"Weekend Coder","subtitle":"Why stop just because it's the weekend?","description":"Awarded to those dedicated developers who don't understand the meaning of downtime.","recipient":[{"avatar":"https://bitbucket.org/account/vishalvazkar/avatar/32/","username":"vishal vazkar","date":"Saturday, January 28, 2017 10:26 PM"}]},{"badge_img":"./img/weekend.jpg","title":"Weekend Coder","subtitle":"Why stop just because it's the weekend?","description":"Awarded to those dedicated developers who don't understand the meaning of downtime.","recipient":[{"avatar":"https://bitbucket.org/account/vishalvazkar/avatar/32/","username":"vishal vazkar","date":"Saturday, January 28, 2017 10:25 PM"}]},{"badge_img":"./img/weekend.jpg","title":"Weekend Coder","subtitle":"Why stop just because it's the weekend?","description":"Awarded to those dedicated developers who don't understand the meaning of downtime.","recipient":[{"avatar":"https://bitbucket.org/account/vishalvazkar/avatar/32/","username":"vishal vazkar","date":"Saturday, January 28, 2017 10:24 PM"}]},{"badge_img":"./img/weekend.jpg","title":"Weekend Coder","subtitle":"Why stop just because it's the weekend?","description":"Awarded to those dedicated developers who don't understand the meaning of downtime.","recipient":[{"avatar":"https://bitbucket.org/account/vishalvazkar/avatar/32/","username":"vishal vazkar","date":"Saturday, January 28, 2017 10:22 PM"}]},{"badge_img":"./img/weekend.jpg","title":"Weekend Coder","subtitle":"Why stop just because it's the weekend?","description":"Awarded to those dedicated developers who don't understand the meaning of downtime.","recipient":[{"avatar":"https://bitbucket.org/account/vishalvazkar/avatar/32/","username":"vishal vazkar","date":"Saturday, January 28, 2017 10:21 PM"}]},{"badge_img":"./img/weekend.jpg","title":"Weekend Coder","subtitle":"Why stop just because it's the weekend?","description":"Awarded to those dedicated developers who don't understand the meaning of downtime.","recipient":[{"avatar":"https://bitbucket.org/account/vishalvazkar/avatar/32/","username":"vishal vazkar","date":"Saturday, January 28, 2017 10:19 PM"}]},{"badge_img":"./img/weekend.jpg","title":"Weekend Coder","subtitle":"Why stop just because it's the weekend?","description":"Awarded to those dedicated developers who don't understand the meaning of downtime.","recipient":[{"avatar":"https://bitbucket.org/account/vishalvazkar/avatar/32/","username":"vishal vazkar","date":"Saturday, January 28, 2017 10:17 PM"}]},{"badge_img":"./img/weekend.jpg","title":"Weekend Coder","subtitle":"Why stop just because it's the weekend?","description":"Awarded to those dedicated developers who don't understand the meaning of downtime.","recipient":[{"avatar":"https://bitbucket.org/account/vishalvazkar/avatar/32/","username":"vishal vazkar","date":"Saturday, January 28, 2017 10:14 PM"}]},{"badge_img":"./img/after-hours.jpg","title":"After Hours","subtitle":"Just five more minutes, mom!","description":"Awarded to those dedicated developers who don't understand the meaning of home time.","recipient":[{"avatar":"https://bitbucket.org/account/richardcane/avatar/32/","username":"Richard Cane","date":"Thursday, January 26, 2017 10:04 PM"}]},{"badge_img":"./img/after-hours.jpg","title":"After Hours","subtitle":"Just five more minutes, mom!","description":"Awarded to those dedicated developers who don't understand the meaning of home time.","recipient":[{"avatar":"https://bitbucket.org/account/richardcane/avatar/32/","username":"Richard Cane","date":"Thursday, January 26, 2017 10:03 PM"}]},{"badge_img":"./img/after-hours.jpg","title":"After Hours","subtitle":"Just five more minutes, mom!","description":"Awarded to those dedicated developers who don't understand the meaning of home time.","recipient":[{"avatar":"https://bitbucket.org/account/richardcane/avatar/32/","username":"Richard Cane","date":"Wednesday, January 25, 2017 9:02 PM"}]},{"badge_img":"./img/after-hours.jpg","title":"After Hours","subtitle":"Just five more minutes, mom!","description":"Awarded to those dedicated developers who don't understand the meaning of home time.","recipient":[{"avatar":"https://bitbucket.org/account/MMTRyan/avatar/32/","username":"Ryan Elliott-Potter","date":"Thursday, January 26, 2017 6:25 PM"}]},{"badge_img":"./img/after-hours.jpg","title":"After Hours","subtitle":"Just five more minutes, mom!","description":"Awarded to those dedicated developers who don't understand the meaning of home time.","recipient":[{"avatar":"https://bitbucket.org/account/jon_gregory/avatar/32/","username":"Jonathan Gregory","date":"Thursday, January 26, 2017 8:46 PM"}]},{"badge_img":"./img/after-hours.jpg","title":"After Hours","subtitle":"Just five more minutes, mom!","description":"Awarded to those dedicated developers who don't understand the meaning of home time.","recipient":[{"avatar":"https://bitbucket.org/account/iayub/avatar/32/","username":"Irfan Ayub","date":"Thursday, January 26, 2017 6:28 PM"}]},{"badge_img":"./img/after-hours.jpg","title":"After Hours","subtitle":"Just five more minutes, mom!","description":"Awarded to those dedicated developers who don't understand the meaning of home time.","recipient":[{"avatar":"https://bitbucket.org/account/bsquire/avatar/32/","username":"Ben Squire","date":"Friday, January 27, 2017 11:54 PM"}]},{"badge_img":"./img/after-hours.jpg","title":"After Hours","subtitle":"Just five more minutes, mom!","description":"Awarded to those dedicated developers who don't understand the meaning of home time.","recipient":[{"avatar":"https://bitbucket.org/account/sunilsmmt/avatar/32/","username":"Sunil Subrai","date":"Thursday, January 26, 2017 11:37 PM"}]},{"badge_img":"./img/after-hours.jpg","title":"After Hours","subtitle":"Just five more minutes, mom!","description":"Awarded to those dedicated developers who don't understand the meaning of home time.","recipient":[{"avatar":"https://bitbucket.org/account/sunilsmmt/avatar/32/","username":"Sunil Subrai","date":"Thursday, January 26, 2017 11:34 PM"}]},{"badge_img":"./img/after-hours.jpg","title":"After Hours","subtitle":"Just five more minutes, mom!","description":"Awarded to those dedicated developers who don't understand the meaning of home time.","recipient":[{"avatar":"https://bitbucket.org/account/sunilsmmt/avatar/32/","username":"Sunil Subrai","date":"Thursday, January 26, 2017 11:34 PM"}]},{"badge_img":"./img/after-hours.jpg","title":"After Hours","subtitle":"Just five more minutes, mom!","description":"Awarded to those dedicated developers who don't understand the meaning of home time.","recipient":[{"avatar":"https://bitbucket.org/account/sunilsmmt/avatar/32/","username":"Sunil Subrai","date":"Thursday, January 26, 2017 11:15 PM"}]},{"badge_img":"./img/after-hours.jpg","title":"After Hours","subtitle":"Just five more minutes, mom!","description":"Awarded to those dedicated developers who don't understand the meaning of home time.","recipient":[{"avatar":"https://bitbucket.org/account/iayub/avatar/32/","username":"Irfan Ayub","date":"Thursday, January 26, 2017 6:13 PM"}]},{"badge_img":"./img/after-hours.jpg","title":"After Hours","subtitle":"Just five more minutes, mom!","description":"Awarded to those dedicated developers who don't understand the meaning of home time.","recipient":[{"avatar":"https://bitbucket.org/account/sunilsmmt/avatar/32/","username":"Sunil Subrai","date":"Wednesday, January 25, 2017 9:16 PM"}]},{"badge_img":"./img/after-hours.jpg","title":"After Hours","subtitle":"Just five more minutes, mom!","description":"Awarded to those dedicated developers who don't understand the meaning of home time.","recipient":[{"avatar":"https://bitbucket.org/account/antbutcher/avatar/32/","username":"Ant Butcher","date":"Thursday, January 26, 2017 11:01 PM"}]},{"badge_img":"./img/after-hours.jpg","title":"After Hours","subtitle":"Just five more minutes, mom!","description":"Awarded to those dedicated developers who don't understand the meaning of home time.","recipient":[{"avatar":"https://bitbucket.org/account/antbutcher/avatar/32/","username":"Ant Butcher","date":"Thursday, January 26, 2017 11:01 PM"}]},{"badge_img":"./img/after-hours.jpg","title":"After Hours","subtitle":"Just five more minutes, mom!","description":"Awarded to those dedicated developers who don't understand the meaning of home time.","recipient":[{"avatar":"https://bitbucket.org/account/antbutcher/avatar/32/","username":"Ant Butcher","date":"Wednesday, January 25, 2017 10:02 PM"}]},{"badge_img":"./img/after-hours.jpg","title":"After Hours","subtitle":"Just five more minutes, mom!","description":"Awarded to those dedicated developers who don't understand the meaning of home time.","recipient":[{"avatar":"https://bitbucket.org/account/antbutcher/avatar/32/","username":"Ant Butcher","date":"Wednesday, January 25, 2017 9:51 PM"}]},{"badge_img":"./img/after-hours.jpg","title":"After Hours","subtitle":"Just five more minutes, mom!","description":"Awarded to those dedicated developers who don't understand the meaning of home time.","recipient":[{"avatar":"https://bitbucket.org/account/antbutcher/avatar/32/","username":"Ant Butcher","date":"Wednesday, January 25, 2017 9:31 PM"}]},{"badge_img":"./img/after-hours.jpg","title":"After Hours","subtitle":"Just five more minutes, mom!","description":"Awarded to those dedicated developers who don't understand the meaning of home time.","recipient":[{"avatar":"https://bitbucket.org/account/antbutcher/avatar/32/","username":"Ant Butcher","date":"Wednesday, January 25, 2017 8:52 PM"}]},{"badge_img":"./img/after-hours.jpg","title":"After Hours","subtitle":"Just five more minutes, mom!","description":"Awarded to those dedicated developers who don't understand the meaning of home time.","recipient":[{"avatar":"https://bitbucket.org/account/antbutcher/avatar/32/","username":"Ant Butcher","date":"Wednesday, January 25, 2017 8:46 PM"}]},{"badge_img":"./img/after-hours.jpg","title":"After Hours","subtitle":"Just five more minutes, mom!","description":"Awarded to those dedicated developers who don't understand the meaning of home time.","recipient":[{"avatar":"https://bitbucket.org/account/antbutcher/avatar/32/","username":"Ant Butcher","date":"Wednesday, January 25, 2017 8:43 PM"}]}]